{
  "name": "BlinkyMap",
  "version": "0.1.0",
  "minFPPVersion": "6.0",
  "description": "Automatically build a 3D xLights model for a pixel-wrapped tree by triangulating pixel positions from a phone camera moved to multiple spots.",
  "author": "BlinkyMap Contributors",
  "homeURL": "https://github.com/wbhartmanii/blinkymap",
  "srcURL": "https://github.com/wbhartmanii/blinkymap/archive/refs/heads/main.zip",
  "bugURL": "https://github.com/wbhartmanii/blinkymap/issues",
  "packageName": "blinkymap",
  "type": "plugin",
  "phpPage": "www/index.php",
  "menu": {
    "text": "BlinkyMap",
    "subtext": "3D Pixel Mapper"
  }
}
